rdconfigs/__init__.py
rdconfigs/grids/__init__.py
rdconfigs/grids/analysis.py
rdconfigs/grids/generate.py
rdconfigs/grids/type_aliases.py
rdconfigs/ui/__init__.py
rdconfigs/ui/ui_tools.py
rdconfigs-0.1.3.dist-info/LICENSE
rdconfigs-0.1.3.dist-info/METADATA
rdconfigs-0.1.3.dist-info/WHEEL
rdconfigs-0.1.3.dist-info/top_level.txt
rdconfigs-0.1.3.dist-info/RECORD
