Metadata-Version: 2.1
Name: rdconfigs
Version: 0.1.3
Summary: Generate, display, and analyze randomly colored grids
Author-email: Ujan RoyBandyopadhyay <ujan.roybandyopadhyay@gmail.com>
Classifier: Programming Language :: Python :: 3
Classifier: License :: OSI Approved :: MIT License
Requires-Python: >=3.10
License-File: LICENSE
Requires-Dist: pygame (>=2.1.2)
